{
  "groups": [
    {
      "name": "cc",
      "type": "dev.bijansaudcontentcalender.contentcalender.config.ContentCalendarProperties",
      "sourceType": "dev.bijansaudcontentcalender.contentcalender.config.ContentCalendarProperties"
    }
  ],
  "properties": [
    {
      "name": "cc.about",
      "type": "java.lang.String",
      "sourceType": "dev.bijansaudcontentcalender.contentcalender.config.ContentCalendarProperties"
    },
    {
      "name": "cc.welcome-message",
      "type": "java.lang.String",
      "sourceType": "dev.bijansaudcontentcalender.contentcalender.config.ContentCalendarProperties"
    }
  ],
  "hints": []
}